rft/__init__.py
rft/client.py
rft/common.py
rft/daemon.py
rft/exceptions.py
rft/i3wm.py
rft/rft.py
rft/tmux.py
rft/version.py
rft/window_manager.py
rft/bin/__init__.py
rft/bin/main_client.py
rft/bin/main_daemon.py
rofi_tmux_ng-0.0.2.dist-info/LICENSE
rofi_tmux_ng-0.0.2.dist-info/METADATA
rofi_tmux_ng-0.0.2.dist-info/WHEEL
rofi_tmux_ng-0.0.2.dist-info/entry_points.txt
rofi_tmux_ng-0.0.2.dist-info/top_level.txt
rofi_tmux_ng-0.0.2.dist-info/RECORD
